edgeyolo_runner/__init__.py
edgeyolo_runner/models/__init__.py
edgeyolo_runner/models/coreml_detector.py
edgeyolo_runner/models/detector.py
edgeyolo_runner/models/onnx_detector.py
edgeyolo_runner/models/tflite_detector.py
edgeyolo_runner-0.2.0.dist-info/METADATA
edgeyolo_runner-0.2.0.dist-info/WHEEL
edgeyolo_runner-0.2.0.dist-info/top_level.txt
edgeyolo_runner-0.2.0.dist-info/RECORD
