Metadata-Version: 2.4
Name: edgeyolo-runner
Version: 0.2.0
Summary: A package for running EdgeYOLO models using ONNX, TensorFlow Lite, and CoreML on images and videos
Author-email: Ramon Hollands <ramonhollands@gmail.com>
Project-URL: Homepage, https://github.com/ramonhollands/edgeyolo_runner
Classifier: Programming Language :: Python :: 3
Classifier: License :: OSI Approved :: Apache Software License
Classifier: Operating System :: OS Independent
Requires-Python: >=3.7
Requires-Dist: numpy>=1.19.0
Requires-Dist: onnxruntime>=1.15.0
Requires-Dist: opencv-python>=4.5.0
Requires-Dist: Pillow>=8.0.0
Provides-Extra: gpu
Requires-Dist: onnxruntime-gpu>=1.15.0; extra == "gpu"
Provides-Extra: tflite
Requires-Dist: tensorflow>=2.8.0; extra == "tflite"
Provides-Extra: coreml
Requires-Dist: coremltools>=6.0; extra == "coreml"
Provides-Extra: all
Requires-Dist: tensorflow>=2.8.0; extra == "all"
Requires-Dist: coremltools>=6.0; extra == "all"
